cgul/__init__.py
cgul/cli.py
cgul/harmonise.py
cgul/translate_coords.py
cgul/version.py
cgul/coordinate_models/__init__.py
cgul/coordinate_models/cads.py
cgul/coordinate_models/cads_coordinates.py
cgul/coordinate_models/legacy_options.py
cgul/tools/__init__.py
cgul/tools/common_unit_fixes.py
cgul/tools/convert_units.py
cgul/tools/error_handler.py
cgul-0.0.4.dist-info/LICENSE
cgul-0.0.4.dist-info/METADATA
cgul-0.0.4.dist-info/WHEEL
cgul-0.0.4.dist-info/entry_points.txt
cgul-0.0.4.dist-info/top_level.txt
cgul-0.0.4.dist-info/RECORD
