Metadata-Version: 2.1
Name: cgul
Version: 0.0.4
Summary: Python package which will be used to ensure consistent data format when working with Xarray type data objects.
License: Apache License
Classifier: Development Status :: 2 - Pre-Alpha
Classifier: Intended Audience :: Science/Research
Classifier: License :: OSI Approved :: Apache Software License
Classifier: Operating System :: OS Independent
Classifier: Programming Language :: Python
Classifier: Programming Language :: Python :: 3
Classifier: Programming Language :: Python :: 3.10
Classifier: Topic :: Scientific/Engineering
License-File: LICENSE
Requires-Dist: cf-units
Requires-Dist: click
Requires-Dist: netcdf4
Requires-Dist: xarray
